{"expireTime":9007200868851661000,"key":"create-remote-file-node-https://res.cloudinary.com/softox/image/upload/v1613219314/SEAHAVEN_LED_Head_Lamp_Flash_Light_Torch_with_Adjustable_Rechargeable_Battery_for_Camping_Trekking_Caving_Hiking_Reading_Running_84f6517031.jpg","val":{"content-type":"image/jpeg","etag":"\"fbf58ca29c72159df7861b511d4e0a75\"","last-modified":"Sat, 13 Feb 2021 12:28:35 GMT","content-length":"64841","date":"Tue, 23 Feb 2021 20:04:29 GMT","connection":"close","cache-control":"public, no-transform, immutable, max-age=2592000","access-control-expose-headers":"Content-Length,Content-Disposition,Content-Range,Etag,Server-Timing,Vary,X-Cld-Error,X-Content-Type-Options","access-control-allow-origin":"*","accept-ranges":"bytes","timing-allow-origin":"*","server":"Cloudinary","strict-transport-security":"max-age=604800","x-content-type-options":"nosniff","server-timing":"akam;dur=153;start=2021-02-23T20:04:29.193Z;desc=miss,rtt;dur=0,cloudinary;dur=113;start=2021-02-23T16:48:10.145Z"}}