{"expireTime":9007200868922394000,"key":"create-remote-file-node-https://res.cloudinary.com/softox/image/upload/v1613160495/Samsung_Galaxy_Tab_A_8_0_Silver_2_GB_RAM_32_GB_Storage_Wi_Fi_4_G_16e569f69f.jpg","val":{"content-type":"image/jpeg","etag":"\"861a82e2493a94a84ff5dbf7e1ddfd20\"","last-modified":"Fri, 12 Feb 2021 20:08:16 GMT","content-length":"22435","date":"Wed, 24 Feb 2021 15:43:22 GMT","connection":"close","cache-control":"public, no-transform, immutable, max-age=2592000","access-control-expose-headers":"Content-Length,Content-Disposition,Content-Range,Etag,Server-Timing,Vary,X-Cld-Error,X-Content-Type-Options","access-control-allow-origin":"*","accept-ranges":"bytes","timing-allow-origin":"*","server":"Cloudinary","strict-transport-security":"max-age=604800","x-content-type-options":"nosniff","server-timing":"akam;dur=17;start=2021-02-24T15:43:22.480Z;desc=hit,rtt;dur=194"}}